gsan/__init__.py
gsan/main.py
gsan-5.0.0.dist-info/LICENSE.md
gsan-5.0.0.dist-info/METADATA
gsan-5.0.0.dist-info/WHEEL
gsan-5.0.0.dist-info/entry_points.txt
gsan-5.0.0.dist-info/top_level.txt
gsan-5.0.0.dist-info/RECORD
