Metadata-Version: 2.1
Name: gsan
Version: 5.0.0
License-File: LICENSE.md
Requires-Dist: typer
Requires-Dist: rich
Requires-Dist: pyasn1
Requires-Dist: cryptography
Requires-Dist: pyOpenSSL
Provides-Extra: dev
Requires-Dist: black; extra == "dev"
